{"HeardMote": [{"RSSI": "-21", "MAC": "Manager", "MoteID": "1"}, {"RSSI": "-36", "MAC": "00-17-0d-00-00-31-d5-67", "MoteID": "7"}, {"RSSI": "-39", "MAC": "00-17-0d-00-00-31-c3-47", "MoteID": "3"}, {"RSSI": "-42", "MAC": "00-17-0d-00-00-31-d1-70", "MoteID": "4"}], "Payload": "A127_20_2_516355547277783608922418523191942809", "BlinkAddress": "00-17-0d-00-00-38-07-0c", "Time": "2019-04-29 17:28:08.874309"}
{"HeardMote": [{"RSSI": "-21", "MAC": "Manager", "MoteID": "1"}, {"RSSI": "-41", "MAC": "00-17-0d-00-00-31-c6-b8", "MoteID": "43"}, {"RSSI": "-40", "MAC": "00-17-0d-00-00-31-c1-c1", "MoteID": "44"}, {"RSSI": "-41", "MAC": "00-17-0d-00-00-31-d1-d3", "MoteID": "8"}], "Payload": "A127_20_2_936682912127980984606314626897119101", "BlinkAddress": "00-17-0d-00-00-38-07-0c", "Time": "2019-04-29 17:28:12.171608"}
{"HeardMote": [{"RSSI": "-22", "MAC": "Manager", "MoteID": "1"}, {"RSSI": "-37", "MAC": "00-17-0d-00-00-31-c6-b8", "MoteID": "43"}, {"RSSI": "-37", "MAC": "00-17-0d-00-00-31-d5-67", "MoteID": "7"}, {"RSSI": "-39", "MAC": "00-17-0d-00-00-31-c3-47", "MoteID": "3"}], "Payload": "A127_20_2_531846492468280204214679828675789857", "BlinkAddress": "00-17-0d-00-00-38-07-0c", "Time": "2019-04-29 17:28:14.579003"}
{"HeardMote": [{"RSSI": "-23", "MAC": "Manager", "MoteID": "1"}, {"RSSI": "-36", "MAC": "00-17-0d-00-00-31-c3-47", "MoteID": "3"}, {"RSSI": "-45", "MAC": "00-17-0d-00-00-31-d5-67", "MoteID": "7"}, {"RSSI": "-46", "MAC": "00-17-0d-00-00-31-d1-70", "MoteID": "4"}], "Payload": "A127_20_2_471030127357183252449487702719775093", "BlinkAddress": "00-17-0d-00-00-38-07-0c", "Time": "2019-04-29 17:28:18.517267"}
{"HeardMote": [{"RSSI": "-21", "MAC": "Manager", "MoteID": "1"}, {"RSSI": "-36", "MAC": "00-17-0d-00-00-31-d5-67", "MoteID": "7"}, {"RSSI": "-40", "MAC": "00-17-0d-00-00-31-c6-b8", "MoteID": "43"}, {"RSSI": "-40", "MAC": "00-17-0d-00-00-31-c3-47", "MoteID": "3"}], "Payload": "A127_20_2_653262746655042843335143407866054751", "BlinkAddress": "00-17-0d-00-00-38-07-0c", "Time": "2019-04-29 17:28:22.373801"}
{"HeardMote": [{"RSSI": "-23", "MAC": "Manager", "MoteID": "1"}, {"RSSI": "-40", "MAC": "00-17-0d-00-00-31-c3-47", "MoteID": "3"}, {"RSSI": "-41", "MAC": "00-17-0d-00-00-31-c6-b8", "MoteID": "43"}, {"RSSI": "-48", "MAC": "00-17-0d-00-00-31-d5-67", "MoteID": "7"}], "Payload": "A127_20_2_31439973262594487763520345830493995", "BlinkAddress": "00-17-0d-00-00-38-07-0c", "Time": "2019-04-29 17:28:26.136235"}
{"HeardMote": [{"RSSI": "-22", "MAC": "Manager", "MoteID": "1"}, {"RSSI": "-35", "MAC": "00-17-0d-00-00-31-d5-67", "MoteID": "7"}, {"RSSI": "-37", "MAC": "00-17-0d-00-00-31-c3-47", "MoteID": "3"}, {"RSSI": "-39", "MAC": "00-17-0d-00-00-31-d1-70", "MoteID": "4"}], "Payload": "A127_20_2_37600459886817209927445503291250823", "BlinkAddress": "00-17-0d-00-00-38-07-0c", "Time": "2019-04-29 17:28:30.103952"}
{"HeardMote": [{"RSSI": "-23", "MAC": "Manager", "MoteID": "1"}, {"RSSI": "-41", "MAC": "00-17-0d-00-00-31-c6-b8", "MoteID": "43"}, {"RSSI": "-42", "MAC": "00-17-0d-00-00-31-c3-47", "MoteID": "3"}, {"RSSI": "-42", "MAC": "00-17-0d-00-00-31-d5-67", "MoteID": "7"}], "Payload": "A127_20_2_481247626992782423860241959821280003", "BlinkAddress": "00-17-0d-00-00-38-07-0c", "Time": "2019-04-29 17:28:33.864556"}
{"HeardMote": [{"RSSI": "-21", "MAC": "Manager", "MoteID": "1"}, {"RSSI": "-50", "MAC": "00-17-0d-00-00-31-c6-b8", "MoteID": "43"}, {"RSSI": "-44", "MAC": "00-17-0d-00-00-31-c2-f9", "MoteID": "33"}, {"RSSI": "-45", "MAC": "00-17-0d-00-00-31-d1-d3", "MoteID": "8"}], "Payload": "A127_20_2_498363334304060426581987489459303007", "BlinkAddress": "00-17-0d-00-00-38-07-0c", "Time": "2019-04-29 17:28:38.215372"}
{"HeardMote": [{"RSSI": "-22", "MAC": "Manager", "MoteID": "1"}, {"RSSI": "-37", "MAC": "00-17-0d-00-00-31-c3-47", "MoteID": "3"}, {"RSSI": "-37", "MAC": "00-17-0d-00-00-31-d5-67", "MoteID": "7"}, {"RSSI": "-40", "MAC": "00-17-0d-00-00-31-d1-70", "MoteID": "4"}], "Payload": "A127_20_2_780673852310274023575064423237257913", "BlinkAddress": "00-17-0d-00-00-38-07-0c", "Time": "2019-04-29 17:28:43.211742"}
{"HeardMote": [{"RSSI": "-23", "MAC": "Manager", "MoteID": "1"}, {"RSSI": "-40", "MAC": "00-17-0d-00-00-31-d5-67", "MoteID": "7"}, {"RSSI": "-41", "MAC": "00-17-0d-00-00-31-c6-b8", "MoteID": "43"}, {"RSSI": "-40", "MAC": "00-17-0d-00-00-31-c1-c1", "MoteID": "44"}], "Payload": "A127_20_2_486368228458929891613961241116854386", "BlinkAddress": "00-17-0d-00-00-38-07-0c", "Time": "2019-04-29 17:28:46.784463"}
{"HeardMote": [{"RSSI": "-22", "MAC": "Manager", "MoteID": "1"}, {"RSSI": "-40", "MAC": "00-17-0d-00-00-31-d5-67", "MoteID": "7"}, {"RSSI": "-44", "MAC": "00-17-0d-00-00-31-c3-47", "MoteID": "3"}, {"RSSI": "-45", "MAC": "00-17-0d-00-00-31-d1-70", "MoteID": "4"}], "Payload": "A127_20_2_283649552283836415440203641430274519", "BlinkAddress": "00-17-0d-00-00-38-07-0c", "Time": "2019-04-29 17:28:53.230225"}
{"HeardMote": [{"RSSI": "-23", "MAC": "Manager", "MoteID": "1"}, {"RSSI": "-34", "MAC": "00-17-0d-00-00-31-c3-47", "MoteID": "3"}, {"RSSI": "-37", "MAC": "00-17-0d-00-00-31-d5-67", "MoteID": "7"}, {"RSSI": "-45", "MAC": "00-17-0d-00-00-31-d1-70", "MoteID": "4"}], "Payload": "A127_20_2_52701933326361583720223367914091975", "BlinkAddress": "00-17-0d-00-00-38-07-0c", "Time": "2019-04-29 17:28:57.086307"}
{"HeardMote": [{"RSSI": "-20", "MAC": "Manager", "MoteID": "1"}, {"RSSI": "-39", "MAC": "00-17-0d-00-00-31-c3-47", "MoteID": "3"}, {"RSSI": "-42", "MAC": "00-17-0d-00-00-31-c6-b8", "MoteID": "43"}, {"RSSI": "-42", "MAC": "00-17-0d-00-00-31-d5-67", "MoteID": "7"}], "Payload": "A127_20_2_22577817919947710871774892764630103", "BlinkAddress": "00-17-0d-00-00-38-07-0c", "Time": "2019-04-29 17:29:00.864305"}
{"HeardMote": [{"RSSI": "-23", "MAC": "Manager", "MoteID": "1"}, {"RSSI": "-36", "MAC": "00-17-0d-00-00-31-c6-b8", "MoteID": "43"}, {"RSSI": "-43", "MAC": "00-17-0d-00-00-31-d5-67", "MoteID": "7"}, {"RSSI": "-55", "MAC": "00-17-0d-00-00-31-d1-70", "MoteID": "4"}], "Payload": "A127_20_2_399915350950914445363258935639887593", "BlinkAddress": "00-17-0d-00-00-38-07-0c", "Time": "2019-04-29 17:29:04.096771"}
{"HeardMote": [{"RSSI": "-22", "MAC": "Manager", "MoteID": "1"}, {"RSSI": "-43", "MAC": "00-17-0d-00-00-31-c6-b8", "MoteID": "43"}, {"RSSI": "-39", "MAC": "00-17-0d-00-00-31-c2-f9", "MoteID": "33"}, {"RSSI": "-44", "MAC": "00-17-0d-00-00-31-d1-d3", "MoteID": "8"}], "Payload": "A127_20_2_859341217858319452711066846903207726", "BlinkAddress": "00-17-0d-00-00-38-07-0c", "Time": "2019-04-29 17:29:08.028292"}
{"HeardMote": [{"RSSI": "-25", "MAC": "Manager", "MoteID": "1"}, {"RSSI": "-39", "MAC": "00-17-0d-00-00-31-c6-b8", "MoteID": "43"}, {"RSSI": "-47", "MAC": "00-17-0d-00-00-31-d5-67", "MoteID": "7"}, {"RSSI": "-56", "MAC": "00-17-0d-00-00-31-d1-70", "MoteID": "4"}], "Payload": "A127_20_2_439571575376601258848941911832768597", "BlinkAddress": "00-17-0d-00-00-38-07-0c", "Time": "2019-04-29 17:29:11.810961"}
{"HeardMote": [{"RSSI": "-24", "MAC": "Manager", "MoteID": "1"}, {"RSSI": "-37", "MAC": "00-17-0d-00-00-31-c3-47", "MoteID": "3"}, {"RSSI": "-43", "MAC": "00-17-0d-00-00-31-c6-b8", "MoteID": "43"}, {"RSSI": "-48", "MAC": "00-17-0d-00-00-31-d1-70", "MoteID": "4"}], "Payload": "A127_20_2_509820060601046554590307659345701763", "BlinkAddress": "00-17-0d-00-00-38-07-0c", "Time": "2019-04-29 17:29:16.279582"}
{"HeardMote": [{"RSSI": "-23", "MAC": "Manager", "MoteID": "1"}, {"RSSI": "-33", "MAC": "00-17-0d-00-00-31-c3-47", "MoteID": "3"}, {"RSSI": "-41", "MAC": "00-17-0d-00-00-31-d5-67", "MoteID": "7"}, {"RSSI": "-46", "MAC": "00-17-0d-00-00-31-d1-70", "MoteID": "4"}], "Payload": "A127_20_2_949539901151479233592824872586432326", "BlinkAddress": "00-17-0d-00-00-38-07-0c", "Time": "2019-04-29 17:29:18.300395"}
{"HeardMote": [{"RSSI": "-24", "MAC": "Manager", "MoteID": "1"}, {"RSSI": "-42", "MAC": "00-17-0d-00-00-31-c3-47", "MoteID": "3"}, {"RSSI": "-42", "MAC": "00-17-0d-00-00-31-d5-67", "MoteID": "7"}, {"RSSI": "-44", "MAC": "00-17-0d-00-00-31-d1-70", "MoteID": "4"}], "Payload": "A127_20_2_680526673363170865902252183496143228", "BlinkAddress": "00-17-0d-00-00-38-07-0c", "Time": "2019-04-29 17:29:22.157663"}
{"HeardMote": [{"RSSI": "-22", "MAC": "Manager", "MoteID": "1"}, {"RSSI": "-38", "MAC": "00-17-0d-00-00-31-c3-47", "MoteID": "3"}, {"RSSI": "-48", "MAC": "00-17-0d-00-00-31-d1-70", "MoteID": "4"}, {"RSSI": "-53", "MAC": "00-17-0d-00-00-31-d5-67", "MoteID": "7"}], "Payload": "A127_20_2_534992979129830698266601181595038938", "BlinkAddress": "00-17-0d-00-00-38-07-0c", "Time": "2019-04-29 17:29:24.477085"}
{"HeardMote": [{"RSSI": "-23", "MAC": "Manager", "MoteID": "1"}, {"RSSI": "-36", "MAC": "00-17-0d-00-00-31-c3-47", "MoteID": "3"}, {"RSSI": "-39", "MAC": "00-17-0d-00-00-31-d5-67", "MoteID": "7"}, {"RSSI": "-42", "MAC": "00-17-0d-00-00-31-c6-b8", "MoteID": "43"}], "Payload": "A127_20_2_111655997125162630917382888392002142", "BlinkAddress": "00-17-0d-00-00-38-07-0c", "Time": "2019-04-29 17:29:26.029700"}
{"HeardMote": [{"RSSI": "-22", "MAC": "Manager", "MoteID": "1"}, {"RSSI": "-41", "MAC": "00-17-0d-00-00-31-c3-47", "MoteID": "3"}, {"RSSI": "-42", "MAC": "00-17-0d-00-00-31-d5-67", "MoteID": "7"}, {"RSSI": "-43", "MAC": "00-17-0d-00-00-31-c6-b8", "MoteID": "43"}], "Payload": "A127_20_2_729077683563606054263383694262590184", "BlinkAddress": "00-17-0d-00-00-38-07-0c", "Time": "2019-04-29 17:29:29.154396"}
{"HeardMote": [{"RSSI": "-25", "MAC": "Manager", "MoteID": "1"}, {"RSSI": "-37", "MAC": "00-17-0d-00-00-31-c3-47", "MoteID": "3"}, {"RSSI": "-41", "MAC": "00-17-0d-00-00-31-d5-67", "MoteID": "7"}, {"RSSI": "-43", "MAC": "00-17-0d-00-00-31-d1-70", "MoteID": "4"}], "Payload": "A127_20_2_11553846363853754216606282542248596", "BlinkAddress": "00-17-0d-00-00-38-07-0c", "Time": "2019-04-29 17:29:33.728749"}
{"HeardMote": [{"RSSI": "-23", "MAC": "Manager", "MoteID": "1"}, {"RSSI": "-37", "MAC": "00-17-0d-00-00-31-c3-47", "MoteID": "3"}, {"RSSI": "-45", "MAC": "00-17-0d-00-00-31-c6-b8", "MoteID": "43"}, {"RSSI": "-47", "MAC": "00-17-0d-00-00-31-d1-70", "MoteID": "4"}], "Payload": "A127_20_2_12284612414900411106169220319356207", "BlinkAddress": "00-17-0d-00-00-38-07-0c", "Time": "2019-04-29 17:29:37.505547"}
{"HeardMote": [{"RSSI": "-23", "MAC": "Manager", "MoteID": "1"}, {"RSSI": "-41", "MAC": "00-17-0d-00-00-31-c3-47", "MoteID": "3"}, {"RSSI": "-43", "MAC": "00-17-0d-00-00-31-d5-67", "MoteID": "7"}, {"RSSI": "-41", "MAC": "00-17-0d-00-00-31-d1-d3", "MoteID": "8"}], "Payload": "A127_20_2_70555386970267719198627288010539096", "BlinkAddress": "00-17-0d-00-00-38-07-0c", "Time": "2019-04-29 17:29:39.514700"}
{"HeardMote": [{"RSSI": "-22", "MAC": "Manager", "MoteID": "1"}, {"RSSI": "-38", "MAC": "00-17-0d-00-00-31-d5-67", "MoteID": "7"}, {"RSSI": "-42", "MAC": "00-17-0d-00-00-31-c3-47", "MoteID": "3"}, {"RSSI": "-42", "MAC": "00-17-0d-00-00-31-d1-70", "MoteID": "4"}], "Payload": "A127_20_2_158407429716992086603490376266692519", "BlinkAddress": "00-17-0d-00-00-38-07-0c", "Time": "2019-04-29 17:29:43.372333"}
{"HeardMote": [{"RSSI": "-22", "MAC": "Manager", "MoteID": "1"}, {"RSSI": "-37", "MAC": "00-17-0d-00-00-31-c3-47", "MoteID": "3"}, {"RSSI": "-46", "MAC": "00-17-0d-00-00-31-d1-70", "MoteID": "4"}, {"RSSI": "-49", "MAC": "00-17-0d-00-00-31-d5-67", "MoteID": "7"}], "Payload": "A127_20_2_7112238622715530254563162800785953", "BlinkAddress": "00-17-0d-00-00-38-07-0c", "Time": "2019-04-29 17:29:45.299992"}
{"HeardMote": [{"RSSI": "-21", "MAC": "Manager", "MoteID": "1"}, {"RSSI": "-38", "MAC": "00-17-0d-00-00-31-d5-67", "MoteID": "7"}, {"RSSI": "-42", "MAC": "00-17-0d-00-00-31-c6-b8", "MoteID": "43"}, {"RSSI": "-42", "MAC": "00-17-0d-00-00-31-c3-47", "MoteID": "3"}], "Payload": "A127_20_2_308946813597404215374303507609359653", "BlinkAddress": "00-17-0d-00-00-38-07-0c", "Time": "2019-04-29 17:29:51.085618"}
{"HeardMote": [{"RSSI": "-22", "MAC": "Manager", "MoteID": "1"}, {"RSSI": "-38", "MAC": "00-17-0d-00-00-31-c3-47", "MoteID": "3"}, {"RSSI": "-49", "MAC": "00-17-0d-00-00-31-d5-67", "MoteID": "7"}, {"RSSI": "-50", "MAC": "00-17-0d-00-00-31-d1-70", "MoteID": "4"}], "Payload": "A127_20_2_4456536903426277991228982631920841", "BlinkAddress": "00-17-0d-00-00-38-07-0c", "Time": "2019-04-29 17:29:52.638930"}
{"HeardMote": [{"RSSI": "-23", "MAC": "Manager", "MoteID": "1"}, {"RSSI": "-31", "MAC": "00-17-0d-00-00-31-c3-47", "MoteID": "3"}, {"RSSI": "-37", "MAC": "00-17-0d-00-00-31-d5-67", "MoteID": "7"}, {"RSSI": "-42", "MAC": "00-17-0d-00-00-31-d1-70", "MoteID": "4"}], "Payload": "A127_20_2_973697055509720112968228727607303953", "BlinkAddress": "00-17-0d-00-00-38-07-0c", "Time": "2019-04-29 17:29:54.942457"}
{"HeardMote": [{"RSSI": "-23", "MAC": "Manager", "MoteID": "1"}, {"RSSI": "-39", "MAC": "00-17-0d-00-00-31-c3-47", "MoteID": "3"}, {"RSSI": "-42", "MAC": "00-17-0d-00-00-31-c6-b8", "MoteID": "43"}, {"RSSI": "-42", "MAC": "00-17-0d-00-00-31-d5-67", "MoteID": "7"}], "Payload": "A127_20_2_705106737301215029672370179831283984", "BlinkAddress": "00-17-0d-00-00-38-07-0c", "Time": "2019-04-29 17:30:00.634950"}
{"HeardMote": [{"RSSI": "-23", "MAC": "Manager", "MoteID": "1"}, {"RSSI": "-38", "MAC": "00-17-0d-00-00-31-d5-67", "MoteID": "7"}, {"RSSI": "-50", "MAC": "00-17-0d-00-00-31-c6-b8", "MoteID": "43"}, {"RSSI": "-45", "MAC": "00-17-0d-00-00-31-d1-ac", "MoteID": "46"}], "Payload": "A127_20_2_476284167339621496782060723477207905", "BlinkAddress": "00-17-0d-00-00-38-07-0c", "Time": "2019-04-29 17:30:03.924871"}
{"HeardMote": [{"RSSI": "-21", "MAC": "Manager", "MoteID": "1"}, {"RSSI": "-38", "MAC": "00-17-0d-00-00-31-c3-47", "MoteID": "3"}, {"RSSI": "-39", "MAC": "00-17-0d-00-00-31-c6-b8", "MoteID": "43"}, {"RSSI": "-42", "MAC": "00-17-0d-00-00-31-d5-67", "MoteID": "7"}], "Payload": "A127_20_2_333003338216252108190411199262640755", "BlinkAddress": "00-17-0d-00-00-38-07-0c", "Time": "2019-04-29 17:30:08.363240"}
{"HeardMote": [{"RSSI": "-21", "MAC": "Manager", "MoteID": "1"}, {"RSSI": "-35", "MAC": "00-17-0d-00-00-31-d5-67", "MoteID": "7"}, {"RSSI": "-41", "MAC": "00-17-0d-00-00-31-c3-47", "MoteID": "3"}, {"RSSI": "-42", "MAC": "00-17-0d-00-00-31-d1-70", "MoteID": "4"}], "Payload": "A127_20_2_166319527170834287684364566672081440", "BlinkAddress": "00-17-0d-00-00-38-07-0c", "Time": "2019-04-29 17:30:12.299531"}
{"HeardMote": [{"RSSI": "-21", "MAC": "Manager", "MoteID": "1"}, {"RSSI": "-35", "MAC": "00-17-0d-00-00-31-c3-47", "MoteID": "3"}, {"RSSI": "-47", "MAC": "00-17-0d-00-00-31-d5-67", "MoteID": "7"}, {"RSSI": "-50", "MAC": "00-17-0d-00-00-31-d1-70", "MoteID": "4"}], "Payload": "A127_20_2_226035015191204221942944787852131637", "BlinkAddress": "00-17-0d-00-00-38-07-0c", "Time": "2019-04-29 17:30:14.249650"}
{"HeardMote": [{"RSSI": "-21", "MAC": "Manager", "MoteID": "1"}, {"RSSI": "-38", "MAC": "00-17-0d-00-00-31-c6-b8", "MoteID": "43"}, {"RSSI": "-39", "MAC": "00-17-0d-00-00-31-d5-67", "MoteID": "7"}, {"RSSI": "-40", "MAC": "00-17-0d-00-00-31-d1-70", "MoteID": "4"}], "Payload": "A127_20_2_56537981487224172797604591717338650", "BlinkAddress": "00-17-0d-00-00-38-07-0c", "Time": "2019-04-29 17:30:17.425574"}
{"HeardMote": [{"RSSI": "-20", "MAC": "Manager", "MoteID": "1"}, {"RSSI": "-37", "MAC": "00-17-0d-00-00-31-d5-67", "MoteID": "7"}, {"RSSI": "-40", "MAC": "00-17-0d-00-00-31-c6-b8", "MoteID": "43"}, {"RSSI": "-36", "MAC": "00-17-0d-00-00-31-c1-c1", "MoteID": "44"}], "Payload": "A127_20_2_310915891522109636782963504984628070", "BlinkAddress": "00-17-0d-00-00-38-07-0c", "Time": "2019-04-29 17:30:21.281890"}
{"HeardMote": [{"RSSI": "-20", "MAC": "Manager", "MoteID": "1"}, {"RSSI": "-33", "MAC": "00-17-0d-00-00-31-d5-67", "MoteID": "7"}, {"RSSI": "-37", "MAC": "00-17-0d-00-00-31-d1-70", "MoteID": "4"}, {"RSSI": "-46", "MAC": "00-17-0d-00-00-31-c6-b8", "MoteID": "43"}], "Payload": "A127_20_2_44513776622909285521643854969246482", "BlinkAddress": "00-17-0d-00-00-38-07-0c", "Time": "2019-04-29 17:30:27.023484"}
{"HeardMote": [{"RSSI": "-18", "MAC": "Manager", "MoteID": "1"}, {"RSSI": "-37", "MAC": "00-17-0d-00-00-31-d5-67", "MoteID": "7"}, {"RSSI": "-39", "MAC": "00-17-0d-00-00-31-c3-47", "MoteID": "3"}, {"RSSI": "-42", "MAC": "00-17-0d-00-00-31-d1-70", "MoteID": "4"}], "Payload": "A127_20_2_6037404222457610112954904662310891", "BlinkAddress": "00-17-0d-00-00-38-07-0c", "Time": "2019-04-29 17:30:33.512231"}
{"HeardMote": [{"RSSI": "-21", "MAC": "Manager", "MoteID": "1"}, {"RSSI": "-39", "MAC": "00-17-0d-00-00-31-c6-b8", "MoteID": "43"}, {"RSSI": "-39", "MAC": "00-17-0d-00-00-31-c1-c1", "MoteID": "44"}, {"RSSI": "-39", "MAC": "00-17-0d-00-00-31-d1-ac", "MoteID": "46"}], "Payload": "A127_20_2_126248017723131695742521418129345354", "BlinkAddress": "00-17-0d-00-00-38-07-0c", "Time": "2019-04-29 17:30:36.978449"}
{"HeardMote": [{"RSSI": "-22", "MAC": "Manager", "MoteID": "1"}, {"RSSI": "-38", "MAC": "00-17-0d-00-00-31-d5-67", "MoteID": "7"}, {"RSSI": "-39", "MAC": "00-17-0d-00-00-31-c3-47", "MoteID": "3"}, {"RSSI": "-40", "MAC": "00-17-0d-00-00-31-c6-b8", "MoteID": "43"}], "Payload": "A127_20_2_418050767625635167213163971593064167", "BlinkAddress": "00-17-0d-00-00-38-07-0c", "Time": "2019-04-29 17:30:39.219043"}
{"HeardMote": [{"RSSI": "-24", "MAC": "Manager", "MoteID": "1"}, {"RSSI": "-36", "MAC": "00-17-0d-00-00-31-c3-47", "MoteID": "3"}, {"RSSI": "-43", "MAC": "00-17-0d-00-00-31-c6-b8", "MoteID": "43"}, {"RSSI": "-53", "MAC": "00-17-0d-00-00-31-d1-70", "MoteID": "4"}], "Payload": "A127_20_2_160204696204432575412618355965282690", "BlinkAddress": "00-17-0d-00-00-38-07-0c", "Time": "2019-04-29 17:30:43.062154"}
{"HeardMote": [{"RSSI": "-23", "MAC": "Manager", "MoteID": "1"}, {"RSSI": "-41", "MAC": "00-17-0d-00-00-31-c6-b8", "MoteID": "43"}, {"RSSI": "-42", "MAC": "00-17-0d-00-00-31-d1-d3", "MoteID": "8"}, {"RSSI": "-43", "MAC": "00-17-0d-00-00-31-c1-c1", "MoteID": "44"}], "Payload": "A127_20_2_340311980168873726385469409606266864", "BlinkAddress": "00-17-0d-00-00-38-07-0c", "Time": "2019-04-29 17:30:47.426437"}
{"HeardMote": [{"RSSI": "-22", "MAC": "Manager", "MoteID": "1"}, {"RSSI": "-39", "MAC": "00-17-0d-00-00-31-c3-47", "MoteID": "3"}, {"RSSI": "-42", "MAC": "00-17-0d-00-00-31-c6-b8", "MoteID": "43"}, {"RSSI": "-51", "MAC": "00-17-0d-00-00-31-d1-70", "MoteID": "4"}], "Payload": "A127_20_2_23866874611146875172673369419762310", "BlinkAddress": "00-17-0d-00-00-38-07-0c", "Time": "2019-04-29 17:30:50.775872"}
{"HeardMote": [{"RSSI": "-21", "MAC": "Manager", "MoteID": "1"}, {"RSSI": "-38", "MAC": "00-17-0d-00-00-31-c3-47", "MoteID": "3"}, {"RSSI": "-41", "MAC": "00-17-0d-00-00-31-d5-67", "MoteID": "7"}, {"RSSI": "-42", "MAC": "00-17-0d-00-00-31-d1-70", "MoteID": "4"}], "Payload": "A127_20_2_536075249652221364911196663932481661", "BlinkAddress": "00-17-0d-00-00-38-07-0c", "Time": "2019-04-29 17:30:54.726336"}
{"HeardMote": [{"RSSI": "-23", "MAC": "Manager", "MoteID": "1"}, {"RSSI": "-41", "MAC": "00-17-0d-00-00-31-c6-b8", "MoteID": "43"}, {"RSSI": "-41", "MAC": "00-17-0d-00-00-31-c3-47", "MoteID": "3"}, {"RSSI": "-43", "MAC": "00-17-0d-00-00-31-d5-67", "MoteID": "7"}], "Payload": "A127_20_2_248713794124359112695954813107725443", "BlinkAddress": "00-17-0d-00-00-38-07-0c", "Time": "2019-04-29 17:30:58.505317"}
{"HeardMote": [{"RSSI": "-24", "MAC": "Manager", "MoteID": "1"}, {"RSSI": "-40", "MAC": "00-17-0d-00-00-31-c3-47", "MoteID": "3"}, {"RSSI": "-47", "MAC": "00-17-0d-00-00-31-c6-b8", "MoteID": "43"}, {"RSSI": "-48", "MAC": "00-17-0d-00-00-31-d5-67", "MoteID": "7"}], "Payload": "A127_20_2_328986209972672428981433359370643092", "BlinkAddress": "00-17-0d-00-00-38-07-0c", "Time": "2019-04-29 17:31:04.289576"}
{"HeardMote": [{"RSSI": "-21", "MAC": "Manager", "MoteID": "1"}, {"RSSI": "-37", "MAC": "00-17-0d-00-00-31-c6-b8", "MoteID": "43"}, {"RSSI": "-39", "MAC": "00-17-0d-00-00-31-c3-47", "MoteID": "3"}, {"RSSI": "-40", "MAC": "00-17-0d-00-00-31-d1-70", "MoteID": "4"}], "Payload": "A127_20_2_757164977807750484492021282143041100", "BlinkAddress": "00-17-0d-00-00-38-07-0c", "Time": "2019-04-29 17:31:08.147642"}
{"HeardMote": [{"RSSI": "-23", "MAC": "Manager", "MoteID": "1"}, {"RSSI": "-37", "MAC": "00-17-0d-00-00-31-c3-47", "MoteID": "3"}, {"RSSI": "-42", "MAC": "00-17-0d-00-00-31-c6-b8", "MoteID": "43"}, {"RSSI": "-44", "MAC": "00-17-0d-00-00-31-d1-70", "MoteID": "4"}], "Payload": "A127_20_2_14583126996495986639988422864353185", "BlinkAddress": "00-17-0d-00-00-38-07-0c", "Time": "2019-04-29 17:31:12.003764"}
{"HeardMote": [{"RSSI": "-22", "MAC": "Manager", "MoteID": "1"}, {"RSSI": "-38", "MAC": "00-17-0d-00-00-31-d5-67", "MoteID": "7"}, {"RSSI": "-40", "MAC": "00-17-0d-00-00-31-c6-b8", "MoteID": "43"}, {"RSSI": "-42", "MAC": "00-17-0d-00-00-31-d1-70", "MoteID": "4"}], "Payload": "A127_20_2_274079549582250630954049858565388382", "BlinkAddress": "00-17-0d-00-00-38-07-0c", "Time": "2019-04-29 17:31:15.861398"}
{"HeardMote": [{"RSSI": "-23", "MAC": "Manager", "MoteID": "1"}, {"RSSI": "-39", "MAC": "00-17-0d-00-00-31-c3-47", "MoteID": "3"}, {"RSSI": "-39", "MAC": "00-17-0d-00-00-31-d5-67", "MoteID": "7"}, {"RSSI": "-41", "MAC": "00-17-0d-00-00-31-d1-70", "MoteID": "4"}], "Payload": "A127_20_2_870109134560955680115220953750506208", "BlinkAddress": "00-17-0d-00-00-38-07-0c", "Time": "2019-04-29 17:31:17.492260"}
{"HeardMote": [{"RSSI": "-22", "MAC": "Manager", "MoteID": "1"}, {"RSSI": "-31", "MAC": "00-17-0d-00-00-31-c3-47", "MoteID": "3"}, {"RSSI": "-36", "MAC": "00-17-0d-00-00-31-c6-b8", "MoteID": "43"}, {"RSSI": "-36", "MAC": "00-17-0d-00-00-31-d5-67", "MoteID": "7"}], "Payload": "A127_20_2_481542494361388417952339457403665743", "BlinkAddress": "00-17-0d-00-00-38-07-0c", "Time": "2019-04-29 17:31:21.726256"}
{"HeardMote": [{"RSSI": "-21", "MAC": "Manager", "MoteID": "1"}, {"RSSI": "-37", "MAC": "00-17-0d-00-00-31-d5-67", "MoteID": "7"}, {"RSSI": "-42", "MAC": "00-17-0d-00-00-31-c3-47", "MoteID": "3"}, {"RSSI": "-42", "MAC": "00-17-0d-00-00-31-d1-70", "MoteID": "4"}], "Payload": "A127_20_2_51963364468915663107157978160028364", "BlinkAddress": "00-17-0d-00-00-38-07-0c", "Time": "2019-04-29 17:31:31.368169"}
{"HeardMote": [{"RSSI": "-21", "MAC": "Manager", "MoteID": "1"}, {"RSSI": "-41", "MAC": "00-17-0d-00-00-31-c6-b8", "MoteID": "43"}, {"RSSI": "-40", "MAC": "00-17-0d-00-00-31-d1-d3", "MoteID": "8"}, {"RSSI": "-43", "MAC": "00-17-0d-00-00-31-c1-c1", "MoteID": "44"}], "Payload": "A127_20_2_23002259774770416950960413077442577", "BlinkAddress": "00-17-0d-00-00-38-07-0c", "Time": "2019-04-29 17:31:34.672484"}
{"HeardMote": [{"RSSI": "-22", "MAC": "Manager", "MoteID": "1"}, {"RSSI": "-36", "MAC": "00-17-0d-00-00-31-d5-67", "MoteID": "7"}, {"RSSI": "-38", "MAC": "00-17-0d-00-00-31-c3-47", "MoteID": "3"}, {"RSSI": "-38", "MAC": "00-17-0d-00-00-31-d1-70", "MoteID": "4"}], "Payload": "A127_20_2_956665942604309139458116241797068964", "BlinkAddress": "00-17-0d-00-00-38-07-0c", "Time": "2019-04-29 17:31:37.168270"}
{"HeardMote": [{"RSSI": "-20", "MAC": "Manager", "MoteID": "1"}, {"RSSI": "-35", "MAC": "00-17-0d-00-00-31-c3-47", "MoteID": "3"}, {"RSSI": "-43", "MAC": "00-17-0d-00-00-31-d1-70", "MoteID": "4"}, {"RSSI": "-37", "MAC": "00-17-0d-00-00-31-d1-d3", "MoteID": "8"}], "Payload": "A127_20_2_989718698853413952166376580880484813", "BlinkAddress": "00-17-0d-00-00-38-07-0c", "Time": "2019-04-29 17:31:41.012249"}
{"HeardMote": [{"RSSI": "-21", "MAC": "Manager", "MoteID": "1"}, {"RSSI": "-38", "MAC": "00-17-0d-00-00-31-d5-67", "MoteID": "7"}, {"RSSI": "-39", "MAC": "00-17-0d-00-00-31-d1-70", "MoteID": "4"}, {"RSSI": "-41", "MAC": "00-17-0d-00-00-31-c6-b8", "MoteID": "43"}], "Payload": "A127_20_2_745157103595043664671347433344071654", "BlinkAddress": "00-17-0d-00-00-38-07-0c", "Time": "2019-04-29 17:31:44.773644"}
{"HeardMote": [{"RSSI": "-20", "MAC": "Manager", "MoteID": "1"}, {"RSSI": "-38", "MAC": "00-17-0d-00-00-31-d5-67", "MoteID": "7"}, {"RSSI": "-39", "MAC": "00-17-0d-00-00-31-c6-b8", "MoteID": "43"}, {"RSSI": "-35", "MAC": "00-17-0d-00-00-31-c1-c1", "MoteID": "44"}], "Payload": "A127_20_2_15936174497821438649441070360097295", "BlinkAddress": "00-17-0d-00-00-38-07-0c", "Time": "2019-04-29 17:31:48.064958"}
{"HeardMote": [{"RSSI": "-22", "MAC": "Manager", "MoteID": "1"}, {"RSSI": "-32", "MAC": "00-17-0d-00-00-31-c3-47", "MoteID": "3"}, {"RSSI": "-36", "MAC": "00-17-0d-00-00-31-d5-67", "MoteID": "7"}, {"RSSI": "-43", "MAC": "00-17-0d-00-00-31-d1-70", "MoteID": "4"}], "Payload": "A127_20_2_203551134840284300661720590295761526", "BlinkAddress": "00-17-0d-00-00-38-07-0c", "Time": "2019-04-29 17:31:50.653591"}
{"HeardMote": [{"RSSI": "-20", "MAC": "Manager", "MoteID": "1"}, {"RSSI": "-37", "MAC": "00-17-0d-00-00-31-c3-47", "MoteID": "3"}, {"RSSI": "-41", "MAC": "00-17-0d-00-00-31-d5-67", "MoteID": "7"}, {"RSSI": "-48", "MAC": "00-17-0d-00-00-31-d1-70", "MoteID": "4"}], "Payload": "A127_20_2_798271067690055231656728643105397438", "BlinkAddress": "00-17-0d-00-00-38-07-0c", "Time": "2019-04-29 17:31:54.511770"}
{"HeardMote": [{"RSSI": "-20", "MAC": "Manager", "MoteID": "1"}, {"RSSI": "-35", "MAC": "00-17-0d-00-00-31-c3-47", "MoteID": "3"}, {"RSSI": "-37", "MAC": "00-17-0d-00-00-31-d5-67", "MoteID": "7"}, {"RSSI": "-50", "MAC": "00-17-0d-00-00-31-c6-b8", "MoteID": "43"}], "Payload": "A127_20_2_891802491947147752209447348495161520", "BlinkAddress": "00-17-0d-00-00-38-07-0c", "Time": "2019-04-29 17:31:59.577969"}
{"HeardMote": [{"RSSI": "-21", "MAC": "Manager", "MoteID": "1"}, {"RSSI": "-38", "MAC": "00-17-0d-00-00-31-c3-47", "MoteID": "3"}, {"RSSI": "-43", "MAC": "00-17-0d-00-00-31-d5-67", "MoteID": "7"}, {"RSSI": "-45", "MAC": "00-17-0d-00-00-31-d1-70", "MoteID": "4"}], "Payload": "A127_20_2_571020167759362542410780475488631478", "BlinkAddress": "00-17-0d-00-00-38-07-0c", "Time": "2019-04-29 17:32:04.153822"}
{"HeardMote": [{"RSSI": "-21", "MAC": "Manager", "MoteID": "1"}, {"RSSI": "-39", "MAC": "00-17-0d-00-00-31-d5-67", "MoteID": "7"}, {"RSSI": "-40", "MAC": "00-17-0d-00-00-31-c3-47", "MoteID": "3"}, {"RSSI": "-44", "MAC": "00-17-0d-00-00-31-c6-b8", "MoteID": "43"}], "Payload": "A127_20_2_250021123109736795784030380296119363", "BlinkAddress": "00-17-0d-00-00-38-07-0c", "Time": "2019-04-29 17:32:08.010079"}
{"HeardMote": [{"RSSI": "-23", "MAC": "Manager", "MoteID": "1"}, {"RSSI": "-33", "MAC": "00-17-0d-00-00-31-c3-47", "MoteID": "3"}, {"RSSI": "-40", "MAC": "00-17-0d-00-00-31-d5-67", "MoteID": "7"}, {"RSSI": "-42", "MAC": "00-17-0d-00-00-31-d1-70", "MoteID": "4"}], "Payload": "A127_20_2_863986932994184350409367952742130065", "BlinkAddress": "00-17-0d-00-00-38-07-0c", "Time": "2019-04-29 17:32:11.868264"}
{"HeardMote": [{"RSSI": "-23", "MAC": "Manager", "MoteID": "1"}, {"RSSI": "-37", "MAC": "00-17-0d-00-00-31-d5-67", "MoteID": "7"}, {"RSSI": "-42", "MAC": "00-17-0d-00-00-31-c6-b8", "MoteID": "43"}, {"RSSI": "-43", "MAC": "00-17-0d-00-00-31-d1-70", "MoteID": "4"}], "Payload": "A127_20_2_372466596924676494166187253930349012", "BlinkAddress": "00-17-0d-00-00-38-07-0c", "Time": "2019-04-29 17:32:15.022024"}
{"HeardMote": [{"RSSI": "-22", "MAC": "Manager", "MoteID": "1"}, {"RSSI": "-37", "MAC": "00-17-0d-00-00-31-c3-47", "MoteID": "3"}, {"RSSI": "-51", "MAC": "00-17-0d-00-00-31-d1-70", "MoteID": "4"}, {"RSSI": "-51", "MAC": "00-17-0d-00-00-31-d5-67", "MoteID": "7"}], "Payload": "A127_20_2_51171686482909797416129707721964913", "BlinkAddress": "00-17-0d-00-00-38-07-0c", "Time": "2019-04-29 17:32:17.652809"}
{"HeardMote": [{"RSSI": "-21", "MAC": "Manager", "MoteID": "1"}, {"RSSI": "-39", "MAC": "00-17-0d-00-00-31-c3-47", "MoteID": "3"}, {"RSSI": "-41", "MAC": "00-17-0d-00-00-31-d5-67", "MoteID": "7"}, {"RSSI": "-43", "MAC": "00-17-0d-00-00-31-d1-70", "MoteID": "4"}], "Payload": "A127_20_2_22226619582226336650098714434681711", "BlinkAddress": "00-17-0d-00-00-38-07-0c", "Time": "2019-04-29 17:32:21.510332"}
{"HeardMote": [{"RSSI": "-23", "MAC": "Manager", "MoteID": "1"}, {"RSSI": "-36", "MAC": "00-17-0d-00-00-31-c3-47", "MoteID": "3"}, {"RSSI": "-41", "MAC": "00-17-0d-00-00-31-c6-b8", "MoteID": "43"}, {"RSSI": "-44", "MAC": "00-17-0d-00-00-31-d5-67", "MoteID": "7"}], "Payload": "A127_20_2_75676834318964766090708759062224562", "BlinkAddress": "00-17-0d-00-00-38-07-0c", "Time": "2019-04-29 17:32:25.781102"}
{"HeardMote": [{"RSSI": "-20", "MAC": "Manager", "MoteID": "1"}, {"RSSI": "-37", "MAC": "00-17-0d-00-00-31-d5-67", "MoteID": "7"}, {"RSSI": "-39", "MAC": "00-17-0d-00-00-31-c3-47", "MoteID": "3"}, {"RSSI": "-45", "MAC": "00-17-0d-00-00-31-d1-70", "MoteID": "4"}], "Payload": "A127_20_2_513180685565838469710136085234595717", "BlinkAddress": "00-17-0d-00-00-38-07-0c", "Time": "2019-04-29 17:32:29.240929"}
{"HeardMote": [{"RSSI": "-21", "MAC": "Manager", "MoteID": "1"}, {"RSSI": "-36", "MAC": "00-17-0d-00-00-31-c6-b8", "MoteID": "43"}, {"RSSI": "-36", "MAC": "00-17-0d-00-00-31-d5-67", "MoteID": "7"}, {"RSSI": "-37", "MAC": "00-17-0d-00-00-31-d1-70", "MoteID": "4"}], "Payload": "A127_20_2_303425975460352926289445042681052542", "BlinkAddress": "00-17-0d-00-00-38-07-0c", "Time": "2019-04-29 17:32:35.177746"}
{"HeardMote": [{"RSSI": "-20", "MAC": "Manager", "MoteID": "1"}, {"RSSI": "-38", "MAC": "00-17-0d-00-00-31-d5-67", "MoteID": "7"}, {"RSSI": "-39", "MAC": "00-17-0d-00-00-31-c6-b8", "MoteID": "43"}, {"RSSI": "-47", "MAC": "00-17-0d-00-00-31-d1-70", "MoteID": "4"}], "Payload": "A127_20_2_2758415745800963016267937635968559", "BlinkAddress": "00-17-0d-00-00-38-07-0c", "Time": "2019-04-29 17:32:38.206167"}
{"HeardMote": [{"RSSI": "-22", "MAC": "Manager", "MoteID": "1"}, {"RSSI": "-38", "MAC": "00-17-0d-00-00-31-c6-b8", "MoteID": "43"}, {"RSSI": "-38", "MAC": "00-17-0d-00-00-31-d5-67", "MoteID": "7"}, {"RSSI": "-45", "MAC": "00-17-0d-00-00-31-d1-70", "MoteID": "4"}], "Payload": "A127_20_2_246892157324023263619093592120227322", "BlinkAddress": "00-17-0d-00-00-38-07-0c", "Time": "2019-04-29 17:32:42.681119"}
{"HeardMote": [{"RSSI": "-23", "MAC": "Manager", "MoteID": "1"}, {"RSSI": "-39", "MAC": "00-17-0d-00-00-31-c3-47", "MoteID": "3"}, {"RSSI": "-48", "MAC": "00-17-0d-00-00-31-d5-67", "MoteID": "7"}, {"RSSI": "-58", "MAC": "00-17-0d-00-00-31-d1-70", "MoteID": "4"}], "Payload": "A127_20_2_356342993913558174416001589134436578", "BlinkAddress": "00-17-0d-00-00-38-07-0c", "Time": "2019-04-29 17:32:46.205172"}
{"HeardMote": [{"RSSI": "-21", "MAC": "Manager", "MoteID": "1"}, {"RSSI": "-39", "MAC": "00-17-0d-00-00-31-d5-67", "MoteID": "7"}, {"RSSI": "-41", "MAC": "00-17-0d-00-00-31-c3-47", "MoteID": "3"}, {"RSSI": "-44", "MAC": "00-17-0d-00-00-31-d1-70", "MoteID": "4"}], "Payload": "A127_20_2_315163852311599139164675476116358658", "BlinkAddress": "00-17-0d-00-00-38-07-0c", "Time": "2019-04-29 17:32:50.439121"}
{"HeardMote": [{"RSSI": "-23", "MAC": "Manager", "MoteID": "1"}, {"RSSI": "-40", "MAC": "00-17-0d-00-00-31-c6-b8", "MoteID": "43"}, {"RSSI": "-41", "MAC": "00-17-0d-00-00-31-c3-47", "MoteID": "3"}, {"RSSI": "-41", "MAC": "00-17-0d-00-00-31-d5-67", "MoteID": "7"}], "Payload": "A127_20_2_8706811783336927075801616342416767", "BlinkAddress": "00-17-0d-00-00-38-07-0c", "Time": "2019-04-29 17:32:54.200457"}
{"HeardMote": [{"RSSI": "-20", "MAC": "Manager", "MoteID": "1"}, {"RSSI": "-33", "MAC": "00-17-0d-00-00-31-c3-47", "MoteID": "3"}, {"RSSI": "-40", "MAC": "00-17-0d-00-00-31-d5-67", "MoteID": "7"}, {"RSSI": "-57", "MAC": "00-17-0d-00-00-31-c6-b8", "MoteID": "43"}], "Payload": "A127_20_2_500198858262804609516303508490853649", "BlinkAddress": "00-17-0d-00-00-38-07-0c", "Time": "2019-04-29 17:32:57.433631"}
{"HeardMote": [{"RSSI": "-21", "MAC": "Manager", "MoteID": "1"}, {"RSSI": "-37", "MAC": "00-17-0d-00-00-31-c3-47", "MoteID": "3"}, {"RSSI": "-42", "MAC": "00-17-0d-00-00-31-c6-b8", "MoteID": "43"}, {"RSSI": "-47", "MAC": "00-17-0d-00-00-31-d1-70", "MoteID": "4"}], "Payload": "A127_20_2_108847955794004583141456768164349982", "BlinkAddress": "00-17-0d-00-00-38-07-0c", "Time": "2019-04-29 17:33:00.002212"}
{"HeardMote": [{"RSSI": "-21", "MAC": "Manager", "MoteID": "1"}, {"RSSI": "-37", "MAC": "00-17-0d-00-00-31-c6-b8", "MoteID": "43"}, {"RSSI": "-37", "MAC": "00-17-0d-00-00-31-d1-70", "MoteID": "4"}, {"RSSI": "-38", "MAC": "00-17-0d-00-00-31-c3-47", "MoteID": "3"}], "Payload": "A127_20_2_248653044309487541326660788928658138", "BlinkAddress": "00-17-0d-00-00-38-07-0c", "Time": "2019-04-29 17:33:03.844417"}
{"HeardMote": [{"RSSI": "-20", "MAC": "Manager", "MoteID": "1"}, {"RSSI": "-35", "MAC": "00-17-0d-00-00-31-c3-47", "MoteID": "3"}, {"RSSI": "-39", "MAC": "00-17-0d-00-00-31-c6-b8", "MoteID": "43"}, {"RSSI": "-46", "MAC": "00-17-0d-00-00-31-d1-70", "MoteID": "4"}], "Payload": "A127_20_2_67521193617091101217981086300701537", "BlinkAddress": "00-17-0d-00-00-38-07-0c", "Time": "2019-04-29 17:33:07.719404"}
{"HeardMote": [{"RSSI": "-21", "MAC": "Manager", "MoteID": "1"}, {"RSSI": "-32", "MAC": "00-17-0d-00-00-31-c3-47", "MoteID": "3"}, {"RSSI": "-38", "MAC": "00-17-0d-00-00-31-c6-b8", "MoteID": "43"}, {"RSSI": "-39", "MAC": "00-17-0d-00-00-31-d5-67", "MoteID": "7"}], "Payload": "A127_20_2_278913479775194898980854565964924553", "BlinkAddress": "00-17-0d-00-00-38-07-0c", "Time": "2019-04-29 17:33:10.934581"}
{"HeardMote": [{"RSSI": "-20", "MAC": "Manager", "MoteID": "1"}, {"RSSI": "-37", "MAC": "00-17-0d-00-00-31-c3-47", "MoteID": "3"}, {"RSSI": "-42", "MAC": "00-17-0d-00-00-31-c6-b8", "MoteID": "43"}, {"RSSI": "-32", "MAC": "00-17-0d-00-00-31-d1-d3", "MoteID": "8"}], "Payload": "A127_20_2_27575549364730612962788518796790203", "BlinkAddress": "00-17-0d-00-00-38-07-0c", "Time": "2019-04-29 17:33:15.414776"}
{"HeardMote": [{"RSSI": "-21", "MAC": "Manager", "MoteID": "1"}, {"RSSI": "-40", "MAC": "00-17-0d-00-00-31-d5-67", "MoteID": "7"}, {"RSSI": "-42", "MAC": "00-17-0d-00-00-31-c6-b8", "MoteID": "43"}, {"RSSI": "-42", "MAC": "00-17-0d-00-00-31-d1-ac", "MoteID": "46"}], "Payload": "A127_20_2_63482686932369541576033531435186291", "BlinkAddress": "00-17-0d-00-00-38-07-0c", "Time": "2019-04-29 17:33:18.706297"}
{"HeardMote": [{"RSSI": "-22", "MAC": "Manager", "MoteID": "1"}, {"RSSI": "-40", "MAC": "00-17-0d-00-00-31-c3-47", "MoteID": "3"}, {"RSSI": "-40", "MAC": "00-17-0d-00-00-31-d5-67", "MoteID": "7"}, {"RSSI": "-48", "MAC": "00-17-0d-00-00-31-d1-70", "MoteID": "4"}], "Payload": "A127_20_2_836258927813187118950196775799633269", "BlinkAddress": "00-17-0d-00-00-38-07-0c", "Time": "2019-04-29 17:33:23.225937"}
{"HeardMote": [{"RSSI": "-18", "MAC": "Manager", "MoteID": "1"}, {"RSSI": "-36", "MAC": "00-17-0d-00-00-31-d5-67", "MoteID": "7"}, {"RSSI": "-37", "MAC": "00-17-0d-00-00-31-c3-47", "MoteID": "3"}, {"RSSI": "-40", "MAC": "00-17-0d-00-00-31-d1-70", "MoteID": "4"}], "Payload": "A127_20_2_5734029229985427029091578597308375", "BlinkAddress": "00-17-0d-00-00-38-07-0c", "Time": "2019-04-29 17:33:27.079932"}
{"HeardMote": [{"RSSI": "-21", "MAC": "Manager", "MoteID": "1"}, {"RSSI": "-36", "MAC": "00-17-0d-00-00-31-c6-b8", "MoteID": "43"}, {"RSSI": "-36", "MAC": "00-17-0d-00-00-31-d5-67", "MoteID": "7"}, {"RSSI": "-37", "MAC": "00-17-0d-00-00-31-c3-47", "MoteID": "3"}], "Payload": "A127_20_2_873574422554568988673201977396257349", "BlinkAddress": "00-17-0d-00-00-38-07-0c", "Time": "2019-04-29 17:33:32.771413"}
{"HeardMote": [{"RSSI": "-20", "MAC": "Manager", "MoteID": "1"}, {"RSSI": "-38", "MAC": "00-17-0d-00-00-31-d5-67", "MoteID": "7"}, {"RSSI": "-40", "MAC": "00-17-0d-00-00-31-c6-b8", "MoteID": "43"}, {"RSSI": "-37", "MAC": "00-17-0d-00-00-31-c1-c1", "MoteID": "44"}], "Payload": "A127_20_2_24164271413883336324458973030746", "BlinkAddress": "00-17-0d-00-00-38-07-0c", "Time": "2019-04-29 17:33:36.061660"}
{"HeardMote": [{"RSSI": "-23", "MAC": "Manager", "MoteID": "1"}, {"RSSI": "-32", "MAC": "00-17-0d-00-00-31-c3-47", "MoteID": "3"}, {"RSSI": "-39", "MAC": "00-17-0d-00-00-31-c6-b8", "MoteID": "43"}, {"RSSI": "-40", "MAC": "00-17-0d-00-00-31-d5-67", "MoteID": "7"}], "Payload": "A127_20_2_291552556364925821855952933186950683", "BlinkAddress": "00-17-0d-00-00-38-07-0c", "Time": "2019-04-29 17:33:39.919674"}
{"HeardMote": [{"RSSI": "-20", "MAC": "Manager", "MoteID": "1"}, {"RSSI": "-40", "MAC": "00-17-0d-00-00-31-c3-47", "MoteID": "3"}, {"RSSI": "-41", "MAC": "00-17-0d-00-00-31-d1-70", "MoteID": "4"}, {"RSSI": "-42", "MAC": "00-17-0d-00-00-31-d5-67", "MoteID": "7"}], "Payload": "A127_20_2_581888247815620011511985648248973343", "BlinkAddress": "00-17-0d-00-00-38-07-0c", "Time": "2019-04-29 17:33:42.509362"}
{"HeardMote": [{"RSSI": "-23", "MAC": "Manager", "MoteID": "1"}, {"RSSI": "-33", "MAC": "00-17-0d-00-00-31-c3-47", "MoteID": "3"}, {"RSSI": "-36", "MAC": "00-17-0d-00-00-31-d5-67", "MoteID": "7"}, {"RSSI": "-45", "MAC": "00-17-0d-00-00-31-d1-70", "MoteID": "4"}], "Payload": "A127_20_2_926369668298354875159209838142112244", "BlinkAddress": "00-17-0d-00-00-38-07-0c", "Time": "2019-04-29 17:33:45.988142"}
{"HeardMote": [{"RSSI": "-20", "MAC": "Manager", "MoteID": "1"}, {"RSSI": "-38", "MAC": "00-17-0d-00-00-31-c3-47", "MoteID": "3"}, {"RSSI": "-39", "MAC": "00-17-0d-00-00-31-d5-67", "MoteID": "7"}, {"RSSI": "-40", "MAC": "00-17-0d-00-00-31-d1-70", "MoteID": "4"}], "Payload": "A127_20_2_208627669169623880919468785259835996", "BlinkAddress": "00-17-0d-00-00-38-07-0c", "Time": "2019-04-29 17:33:48.293972"}
{"HeardMote": [{"RSSI": "-21", "MAC": "Manager", "MoteID": "1"}, {"RSSI": "-39", "MAC": "00-17-0d-00-00-31-d5-67", "MoteID": "7"}, {"RSSI": "-40", "MAC": "00-17-0d-00-00-31-c3-47", "MoteID": "3"}, {"RSSI": "-46", "MAC": "00-17-0d-00-00-31-d1-70", "MoteID": "4"}], "Payload": "A127_20_2_359811203242878392164739691392949155", "BlinkAddress": "00-17-0d-00-00-38-07-0c", "Time": "2019-04-29 17:33:52.151997"}
{"HeardMote": [{"RSSI": "-20", "MAC": "Manager", "MoteID": "1"}, {"RSSI": "-38", "MAC": "00-17-0d-00-00-31-d5-67", "MoteID": "7"}, {"RSSI": "-39", "MAC": "00-17-0d-00-00-31-c3-47", "MoteID": "3"}, {"RSSI": "-41", "MAC": "00-17-0d-00-00-31-d1-70", "MoteID": "4"}], "Payload": "A127_20_2_254224805938018087116794674906369374", "BlinkAddress": "00-17-0d-00-00-38-07-0c", "Time": "2019-04-29 17:33:56.008543"}
{"HeardMote": [{"RSSI": "-21", "MAC": "Manager", "MoteID": "1"}, {"RSSI": "-39", "MAC": "00-17-0d-00-00-31-c6-b8", "MoteID": "43"}, {"RSSI": "-42", "MAC": "00-17-0d-00-00-31-d1-d3", "MoteID": "8"}, {"RSSI": "-42", "MAC": "00-17-0d-00-00-31-d1-ac", "MoteID": "46"}], "Payload": "A127_20_2_70472794553718319213526746936739163", "BlinkAddress": "00-17-0d-00-00-38-07-0c", "Time": "2019-04-29 17:33:59.292424"}
{"HeardMote": [{"RSSI": "-22", "MAC": "Manager", "MoteID": "1"}, {"RSSI": "-38", "MAC": "00-17-0d-00-00-31-d1-70", "MoteID": "4"}, {"RSSI": "-38", "MAC": "00-17-0d-00-00-31-d5-67", "MoteID": "7"}, {"RSSI": "-46", "MAC": "00-17-0d-00-00-31-c6-b8", "MoteID": "43"}], "Payload": "A127_20_2_42779022729676573278207527155049289", "BlinkAddress": "00-17-0d-00-00-38-07-0c", "Time": "2019-04-29 17:34:03.061843"}
{"HeardMote": [{"RSSI": "-22", "MAC": "Manager", "MoteID": "1"}, {"RSSI": "-38", "MAC": "00-17-0d-00-00-31-c3-47", "MoteID": "3"}, {"RSSI": "-48", "MAC": "00-17-0d-00-00-31-d1-70", "MoteID": "4"}, {"RSSI": "-49", "MAC": "00-17-0d-00-00-31-d5-67", "MoteID": "7"}], "Payload": "A127_20_2_689184472804989659527752602586008833", "BlinkAddress": "00-17-0d-00-00-38-07-0c", "Time": "2019-04-29 17:34:05.651015"}
{"HeardMote": [{"RSSI": "-24", "MAC": "Manager", "MoteID": "1"}, {"RSSI": "-39", "MAC": "00-17-0d-00-00-31-d5-67", "MoteID": "7"}, {"RSSI": "-41", "MAC": "00-17-0d-00-00-31-c6-b8", "MoteID": "43"}, {"RSSI": "-45", "MAC": "00-17-0d-00-00-31-c3-47", "MoteID": "3"}], "Payload": "A127_20_2_381470970921105796643094494473207504", "BlinkAddress": "00-17-0d-00-00-38-07-0c", "Time": "2019-04-29 17:34:10.072857"}
{"HeardMote": [{"RSSI": "-25", "MAC": "Manager", "MoteID": "1"}, {"RSSI": "-36", "MAC": "00-17-0d-00-00-31-c3-47", "MoteID": "3"}, {"RSSI": "-37", "MAC": "00-17-0d-00-00-31-c6-b8", "MoteID": "43"}, {"RSSI": "-40", "MAC": "00-17-0d-00-00-31-d5-67", "MoteID": "7"}], "Payload": "A127_20_2_8376713915708066991421431897682573", "BlinkAddress": "00-17-0d-00-00-38-07-0c", "Time": "2019-04-29 17:34:15.293062"}
{"HeardMote": [{"RSSI": "-23", "MAC": "Manager", "MoteID": "1"}, {"RSSI": "-43", "MAC": "00-17-0d-00-00-31-c3-47", "MoteID": "3"}, {"RSSI": "-44", "MAC": "00-17-0d-00-00-31-c6-b8", "MoteID": "43"}, {"RSSI": "-47", "MAC": "00-17-0d-00-00-31-d5-67", "MoteID": "7"}], "Payload": "A127_20_2_90448653575734867642477251862738234", "BlinkAddress": "00-17-0d-00-00-38-07-0c", "Time": "2019-04-29 17:34:19.056987"}
{"HeardMote": [{"RSSI": "-23", "MAC": "Manager", "MoteID": "1"}, {"RSSI": "-37", "MAC": "00-17-0d-00-00-31-c6-b8", "MoteID": "43"}, {"RSSI": "-37", "MAC": "00-17-0d-00-00-31-d1-d3", "MoteID": "8"}, {"RSSI": "-41", "MAC": "00-17-0d-00-00-31-d1-ac", "MoteID": "46"}], "Payload": "A127_20_2_54418782768553197545420660299397372", "BlinkAddress": "00-17-0d-00-00-38-07-0c", "Time": "2019-04-29 17:34:22.376322"}
